setup.py
harbor_py.egg-info/PKG-INFO
harbor_py.egg-info/SOURCES.txt
harbor_py.egg-info/dependency_links.txt
harbor_py.egg-info/top_level.txt
harborclient/__init__.py
harborclient/harborclient.py
harborclient/test_harborclient.py