Metadata-Version: 1.1
Name: harbor-py
Version: 1.2.0
Summary: The missing harbor python SDK
Home-page: https://github.com/tobegit3hub/harbor-py
Author: tobe
Author-email: tobeg3oogle@gmail.com
License: Apache Software
Keywords: docker registry distribution harbor python sdk
Platform: UNKNOWN
Classifier: Development Status :: 3 - Alpha
Classifier: Intended Audience :: Developers
Classifier: Topic :: Software Development :: Build Tools
Classifier: License :: OSI Approved :: Apache Software License
Classifier: Programming Language :: Python :: 2
Classifier: Programming Language :: Python :: 2.6
Classifier: Programming Language :: Python :: 2.7
Classifier: Programming Language :: Python :: 3
Classifier: Programming Language :: Python :: 3.3
Classifier: Programming Language :: Python :: 3.4
Classifier: Programming Language :: Python :: 3.5
